moredata/__init__.py
moredata/datasets/__init__.py
moredata/enricher/__init__.py
moredata/enricher/enricher.py
moredata/enricher/enricher_builder.py
moredata/enricher/api_connector/__init__.py
moredata/enricher/api_connector/api_connector.py
moredata/enricher/elasticsearch_connector/__init__.py
moredata/enricher/elasticsearch_connector/elasticsearch_connector.py
moredata/enricher/elasticsearch_connector/index_handler.py
moredata/enricher/elasticsearch_connector/pipeline_handler.py
moredata/enricher/elasticsearch_connector/policy_handler.py
moredata/enricher/osm/__init__.py
moredata/enricher/osm/functional_region_connector.py
moredata/enricher/osm/osm_places_connector.py
moredata/enricher/sql_connector/__init__.py
moredata/enricher/sql_connector/sql_connector.py
moredata/models/__init__.py
moredata/models/data.py
moredata/parser/__init__.py
moredata/tests/__init__.py
moredata/tests/test_datasets.py
moredata/utils/__init__.py
moredata/utils/osm_downloader.py
moredata-0.2.6.dist-info/LICENSE.txt
moredata-0.2.6.dist-info/METADATA
moredata-0.2.6.dist-info/WHEEL
moredata-0.2.6.dist-info/top_level.txt
moredata-0.2.6.dist-info/RECORD
