Metadata-Version: 2.1
Name: moredata
Version: 0.2.6
Summary: UNKNOWN
Home-page: https://https://github.com/NESPEDUFV/more-data
License: UNKNOWN
Download-URL: https://github.com/NESPEDUFV/more-data/archive/v0.2.6.tar.gz
Platform: UNKNOWN
Requires-Python: >=3.8
License-File: LICENSE.txt
Requires-Dist: PyMySQL (==0.10.0)
Requires-Dist: Rtree (==1.0.1)
Requires-Dist: SQLAlchemy (==1.4.37)
Requires-Dist: dask-geopandas (==0.2.0)
Requires-Dist: elasticsearch (==7.17.0)
Requires-Dist: geopandas (>=0.10.2)
Requires-Dist: geopy (==2.0.0)
Requires-Dist: h3 (==3.4.3)
Requires-Dist: numpy (>=1.18.1)
Requires-Dist: osm2geojson (==0.1.27)
Requires-Dist: pandas (>=1.0.1)
Requires-Dist: pyproj (==3.5.0)
Requires-Dist: requests (==2.28.2)
Requires-Dist: shapely (>=1.8)
